aihuber/__init__.py
aihuber/aihuber.py
aihuber/logger.py
aihuber/proxy.json
aihuber/py.typed
aihuber/schema.py
aihuber/providers/__init__.py
aihuber/providers/abstract_api.py
aihuber/providers/anthropic/__init__.py
aihuber/providers/anthropic/anthropic_api.py
aihuber/providers/aws_bedrock/__init__.py
aihuber/providers/azure_openai/__init__.py
aihuber/providers/cohere/__init__.py
aihuber/providers/cohere/cohere_api.py
aihuber/providers/google_gemini/__init__.py
aihuber/providers/hugging_face/__init__.py
aihuber/providers/hugging_face/hugging_face_api.py
aihuber/providers/mistralai/__init__.py
aihuber/providers/mistralai/mistralai_api.py
aihuber/providers/openai/__init__.py
aihuber/providers/openai/openai_api.py
aihuber/providers/perplexity/__init__.py
aihuber/providers/perplexity/perplexity_api.py
aihuber/providers/replicate/__init__.py
aihuber/providers/togetherai/__init__.py
aihuber/providers/togetherai/togetherai_api.py
aihuber/providers/xai_grok/__init__.py
aihuber-0.3.0.dist-info/METADATA
aihuber-0.3.0.dist-info/WHEEL
aihuber-0.3.0.dist-info/entry_points.txt
aihuber-0.3.0.dist-info/licenses/LICENSE
aihuber-0.3.0.dist-info/RECORD
