Metadata-Version: 2.4
Name: aihuber
Version: 0.3.0
Summary: ⚡ Python AI SDK - OpenAI, MistralAI, Anthropic, Google Gemini, XAI Grok, Hugging Face
Project-URL: homepage, https://github.com/sylvainmouquet/aihuber
Project-URL: documentation, https://github.com/sylvainmouquet/aihuber
Project-URL: repository, https://github.com/sylvainmouquet/aihuber
Project-URL: changelog, https://github.com/sylvainmouquet/aihuber/releases
Author-email: Sylvain Mouquet <sylvain.mouquet@gmail.com>
License: MIT
License-File: LICENSE
Keywords: llm,python
Classifier: Development Status :: 5 - Production/Stable
Classifier: Framework :: Pytest
Classifier: Intended Audience :: Developers
Classifier: License :: OSI Approved :: MIT License
Classifier: Programming Language :: Python
Classifier: Programming Language :: Python :: 3
Classifier: Programming Language :: Python :: 3.13
Classifier: Topic :: Software Development :: Libraries :: Python Modules
Requires-Python: >=3.13
Requires-Dist: asgi-lifespan>=2.1.0
Requires-Dist: jinja2>=3.1.6
Requires-Dist: nest-asyncio>=1.6.0
Requires-Dist: proxycraft>=1.0.3
